{
    "game_name": "Catch the Spy",
    "start_game": "Start Game",
    "player_count": "Number of Players:",
    "timer_label": "Timer:",
    "back_to_start": "Back to Start",
    "restart_game": "Restart Game",
    "time_up": "Time's up!",
    "unrevealed_card": "Unrevealed",
    "spy_card": "SPY",
    "reveal_card": "Reveal Card",
    "settings": "Settings",
    "player": "Player",
    "used_card": "USED",
    "locations": [
        "Museum",
        "Shopping Mall",
        "Hospital",
        "Park",
        "Restaurant",
        "Library",
        "Beach",
        "Cinema",
        "Zoo",
        "Gym",
        "Airplane",
        "Bank",
        "Hotel",
        "Military Base",
        "Pirate Ship",
        "School",
        "Space station",
        "Submarine",
        "Construction Site",
        "Jail",
        "Night Club",
        "Retirement Home",
        "Stadium",
        "Wedding",
        "Gas Station",
        "Ocean Liner",
        "Office",
        "Hot Tub",
        "Casino",
        "Cemetary"
      ]
  }